{
  "_id": "5fecbcf69b661c0917d13a02",
  "ED_Division": "GA",
  "ED_DecisionNumber": "71/418",
  "ED_Type": "Elections and Appointments",
  "ED_Title": "Confirmation of the appointment of the Administrator of the United Nations Development Programme",
  "ED_AgendaItem": "115 (j)",
  "ED_Plenary_Committee": "Plenary",
  "ED_Session": "71st session of the General Assembly",
  "ED_OriginatingBody": "Plenary",
  "ED_DecisionText": "At its 76th plenary meeting, on 19 April 2017, the General Assembly confirmed the appointment by the Secretary-General of Mr. Achim STEINER of Germany as Administrator of the United Nations Development Programme for a four-year term of office. \r\n\r\nSubsequently, the Secretary-General informed the General Assembly that Mr. Achim STEINER\u2019s term of office would be from 17 June 2017 to 16 June 2021.\r\n\r\n(See A/71/871 and Add.1; A/71/PV.76)",
  "ED_Disclaimer": "The final text of this decision will be contained in document A/71/49 (Vol. III) after editorial review.",
  "ED_MarkNew": false,
  "ED_MarkUpdated": false,
  "DEC_NotificationSent": true,
  "ED_Meeting": [
    {
      "ED_Date": "2017-04-19T05:00:00.000Z",
      "ED_Number": "76th plenary meeting"
    }
  ]
}