{
  "_id": "5fecbd029b661c0917d13b97",
  "ED_Division": "GA",
  "ED_DecisionNumber": "74/503 A and B",
  "ED_Type": "Other Decisions",
  "ED_Title": "Adoption of the agenda and allocation of agenda items ",
  "ED_AgendaItem": "7",
  "ED_Plenary_Committee": "Plenary",
  "ED_Session": "74th session of the General Assembly",
  "ED_OriginatingBody": "Plenary",
  "ED_DecisionText": "A\r\n\r\n\tAt its 2nd plenary meeting, on 20 September 2019, the General Assembly, on the recommendation of the General Committee as set forth in its first report,  adopted the agenda  and the allocation of agenda items  for the seventy-fourth session.\r\n\r\n\tAt the same meeting, the General Assembly, on the recommendation of the General Committee as set forth in its first report,  decided to include in the agenda of its seventy-fourth session the item entitled \u201cQuestion of the Comorian island of Mayotte\u201d, under heading B (Maintenance of international peace and security), on the understanding that there would be no consideration of this item by the Assembly.\r\n\r\n\tAlso at the same meeting, the General Assembly, on the recommendation of the General Committee as set forth in its first report,  decided to defer consideration of the item entitled \u201cQuestion of the Malagasy islands of Glorieuses, Juan de Nova, Europa and Bassas da India\u201d and to include it in the provisional agenda of its seventy-fifth session.\r\n\r\n\tAlso at the same meeting, the General Assembly, on the recommendation of the General Committee as set forth in its first report,  by a recorded vote of 79 to 13, with 17 abstentions,  decided to include in the agenda of its seventy-fourth session an item entitled \u201cThe responsibility to protect and the prevention of genocide, war crimes, ethnic cleansing and crimes against humanity\u201d under heading I (Organizational, administrative and other matters). \r\n\r\nAt its 19th plenary meeting, on 23 October 2019, the General Assembly, on the proposal of the Secretary-General,  having waived the relevant provisions of rule 40 of its rules of procedure, decided to include in the agenda of its seventy-fourth session an additional sub-item entitled \u201cAppointment of members and alternate members of the United Nations Staff Pension Committee\u201d, as sub-item (j) of agenda item 115 entitled \u201cAppointments to fill vacancies in subsidiary organs and other appointments\u201d under heading I (Organizational, administrative and other matters), and to allocate it to the Fifth Committee.\r\n\r\nAt its 52nd plenary meeting, on 19 December 2019, the General Assembly decided to consider directly in the plenary meeting sub-item (b) entitled \u201cInternational financial system and development\u201d of agenda item 17 entitled \u201cMacroeconomic policy questions\u201d, under heading A (Promotion of sustained economic growth and sustainable development in accordance with the relevant resolutions of the General Assembly and recent United Nations conferences), and to proceed expeditiously with the consideration of a draft resolution (A/74/L.38). \r\n\r\nB \r\n\r\nOn 31 March 2020, the General Assembly decided to consider directly in plenary agenda item 163 entitled \u201cFinancing of the African Union-United Nations Hybrid Operation in Darfur\u201d, under heading I (Organizational, administrative and other matters), and to proceed expeditiously with the consideration of a draft resolution (A/74/L.50).   \r\n\r\nOn 2 April 2020, the General Assembly decided to reopen consideration of agenda item 79 entitled \u201cReport of the International Law Commission on the work of its seventy-first session\u201d, under heading F (Promotion of justice and international law), and to consider it directly in plenary in order to proceed expeditiously with the consideration of a draft decision (A/74/L.45).  \r\n\r\nOn 2 April 2020, the General Assembly decided to reopen consideration of sub-item (b) entitled \u201cReport of the Disarmament Commission\u201d of  agenda item 100 entitled \u201cReview of the implementation of the recommendations and decisions adopted by the General Assembly at its tenth special session\u201d, under heading G (Disarmament), and to consider it directly in plenary in order to proceed expeditiously with the consideration of a draft decision (A/74/L.43).   \r\n\r\nOn 13 April 2020, the General Assembly decided to reopen consideration of agenda item 106 entitled \u201cCrime prevention and criminal justice\u201d, under heading H (Drug control, crime prevention and combating international terrorism in all its forms and manifestations), and to consider it directly in plenary in order to proceed expeditiously with the consideration of a draft decision (A/74/L.47).\r\n\r\nOn 13 April 2020, the General Assembly decided to reopen consideration of sub-item (b) entitled \u201cAppointment of members of the Committee on Contributions\u201d of agenda item 115 entitled \u201cAppointments to fill vacancies in subsidiary organs and other appointments\u201d, under heading I (Organizational, administrative and other matters), and to proceed expeditiously with the consideration of the report of the Fifth Committee (A/74/525/Add.2).\r\n\r\nOn 13 April 2020, the General Assembly decided to consider directly in plenary agenda item 133 entitled \u201cReview of the efficiency of the administrative and financial functioning of the United Nations\u201d, under heading I (Organizational, administrative and other matters), and to proceed expeditiously with the consideration of a draft resolution (A/74/L.53) and a draft decision (A/74/L.54). \r\n\r\nOn 13 April 2020, the General Assembly decided to consider directly in plenary agenda item 147 entitled \u201cFinancing of the International Residual Mechanism for Criminal Tribunals\u201d, under heading I (Organizational, administrative and other matters), and to proceed expeditiously with the consideration of a draft resolution (A/74/L.55).\r\n\r\n\r\nOn 14 May 2020, the General Assembly decided to reopen consideration of sub-item (e) entitled \u201cImplementation of the United Nations Convention to Combat Desertification in Those Countries Experiencing Serious Drought and/or Desertification, Particularly in Africa\u201d of agenda item 19 entitled \u201cSustainable development\u201d, under heading A (Promotion of sustained economic growth and sustainable development in accordance with the relevant resolutions of the General Assembly and recent United Nations conferences), and to consider it directly in plenary in order to proceed expeditiously with the consideration of a draft decision (A/74/L.60). \r\n\r\nOn 14 May 2020, the General Assembly decided to consider directly in plenary sub-item (b) entitled \u201cSouth-South cooperation for development\u201d of agenda item 23 entitled \u201cOperational activities for development\u201d, under heading A (Promotion of sustained economic growth and sustainable development in accordance with the relevant resolutions of the General Assembly and recent United Nations conferences), and to proceed expeditiously with the consideration of a draft decision (A/74/L.64).\r\n\r\nOn 11 August 2020, the General Assembly decided to consider directly in plenary sub-item (a) entitled \u201cFollow-up to the Fourth United Nations Conference on the Least Developed Countries\u201d of agenda item 21 entitled \u201cGroups of countries in special situations\u201d, under heading A (Promotion of sustained economic growth and sustainable development in accordance with the relevant resolutions of the General Assembly and recent United Nations conferences), and proceed expeditiously with the consideration of a draft resolution (A/74/L.74). \r\n\r\nOn 11 August 2020, the General Assembly decided to reopen consideration of sub-item (a) \u201cOperational activities for development of the United Nations system\u201d of agenda item 23 entitled \u201cOperational activities for development\u201d, under heading A (Promotion of sustained economic growth and sustainable development in accordance with the relevant resolutions of the General Assembly and recent United Nations conferences), and to consider it directly in plenary in order to proceed expeditiously with the consideration of a draft resolution (A/74/L.77). \r\n\r\nOn 12 August 2020, the General Assembly decided to reopen consideration of agenda item 67 entitled \u201cRights of indigenous peoples\u201d, under heading D (Promotion of human rights), and to consider it directly in plenary in order to proceed expeditiously with the consideration of a draft decision (A/74/L.81). \r\n\r\nOn 14 August 2020, the General Assembly decided to reopen consideration of agenda item 107 entitled \u201cCountering the use of information and communications technologies for criminal purposes\u201d, under heading H (Drug control, crime prevention and combating international terrorism in all its forms and manifestations), and to consider it directly in plenary in order to proceed expeditiously with the consideration of a draft decision (A/74/L.84). \r\n\r\nOn 31 August 2020, the General Assembly decided to reopen consideration of sub-item (a) \u201cAppointment of members of the Advisory Committee on Administrative and Budgetary Questions\u201d of agenda item 105 entitled \u201cAppointments to fill vacancies in subsidiary organs and other appointments\u201d, under heading H (Drug control, crime prevention and combating international terrorism in all its forms and manifestations), and to consider it directly in plenary in order to proceed expeditiously with the consideration of the appointment (A/74/101/Add.2). \r\n\r\nAt the 64th plenary meeting, on 11 September 2020, the General Assembly decided to reopen consideration of agenda item 120 entitled \u201cImplementation of the resolutions of the United Nations\u201d, under heading I (Organizational, administrative and other matters), and to proceed expeditiously with the consideration of the draft resolution (A/74/L.92) and the draft amendment (A/74/L.93). \r\n\r\n",
  "ED_Disclaimer": "Decision 74/503, in section B.1 of the Official Records of the General Assembly, Seventy-fourth Session, Supplement No. 49 (A/74/49), vol. II, becomes decision 74/503 A. The final version of decisions adopted during the main part of the session is contained in the official record of the GA (A/74/49 (Vol. II)) after editorial review.\r\n\r\nThe final version of decisions adopted during the resumed part of the session will be contained in the official record of the GA (A/74/49 (Vol. III)) after editorial review.\r\n",
  "ED_MarkNew": false,
  "ED_MarkUpdated": true,
  "DEC_NotificationSent": true,
  "ED_Meeting": [
    {
      "ED_Date": "2020-09-11T05:00:00.000Z",
      "ED_Number": "64th plenary meeting"
    },
    {
      "ED_Date": "2020-08-31T05:00:00.000Z",
      "ED_Number": "N.A. plenary meeting"
    },
    {
      "ED_Date": "2020-08-14T05:00:00.000Z",
      "ED_Number": "N.A. plenary meeting"
    },
    {
      "ED_Date": "2020-08-12T05:00:00.000Z",
      "ED_Number": "N.A. plenary meeting"
    },
    {
      "ED_Date": "2020-08-11T05:00:00.000Z",
      "ED_Number": "N.A. plenary meeting"
    },
    {
      "ED_Date": "2020-05-14T05:00:00.000Z",
      "ED_Number": "N.A. plenary meeting"
    },
    {
      "ED_Date": "2020-04-13T05:00:00.000Z",
      "ED_Number": "N.A. plenary meeting"
    },
    {
      "ED_Date": "2020-04-02T05:00:00.000Z",
      "ED_Number": "N.A. plenary meeting"
    },
    {
      "ED_Date": "2020-03-31T05:00:00.000Z",
      "ED_Number": "N.A. plenary meeting"
    },
    {
      "ED_Date": "2019-12-19T05:00:00.000Z",
      "ED_Number": "52nd plenary meeting"
    },
    {
      "ED_Date": "2019-10-23T05:00:00.000Z",
      "ED_Number": "19th plenary meeting"
    },
    {
      "ED_Date": "2019-09-20T05:00:00.000Z",
      "ED_Number": "2nd plenary meeting"
    }
  ]
}