{
  "_id": "673627c0ad75f04746d797c3",
  "ED_Division": "GA",
  "ED_DecisionNumber": "79/404",
  "ED_Type": "Elections and Appointments",
  "ED_Title": "Election of members of the Committee for Programme and Coordination",
  "ED_Meeting": [
    {
      "ED_Date": "2024-11-13T05:00:00.000Z",
      "ED_Number": "38th plenary meeting",
      "_id": "673627c0ad75f04746d797c4"
    }
  ],
  "ED_AgendaItem": "115(a)",
  "ED_Plenary_Committee": "Plenary",
  "ED_Session": "79th session of the General Assembly",
  "ED_OriginatingBody": "Plenary",
  "ED_DecisionText": "At its 38th plenary meeting, on 13 November 2024, the General Assembly, on the basis of nominations by the Economic and Social Council (footnote: See A/79/522; see also Economic and Social Council decision 2024/204 B.) and in accordance with the annex to Council resolution 2008 (LX) of 14 May 1976 and Assembly decision 42/450 of 17 December 1987, elected BELGIUM, BOTSWANA, FRANCE, HAITI, KENYA, PARAGUAY and the RUSSIAN FEDERATION as members of the Committee for Programme and Coordination for a three-year term of office beginning on 1 January 2025 to fill the vacancies occurring on the expiration of the terms of office of BELGIUM, BOTSWANA, CHILE, FRANCE, KENYA, PARAGUAY and the RUSSIAN FEDERATION. \n\nAs a result, as of 1 January 2025, the Committee for Programme and Coordination is composed of the following 34 Member States: ARGENTINA,* ARMENIA,** BELGIUM,*** BOTSWANA,*** BRAZIL,** BULGARIA,** CAMEROON,** CHINA,* COSTA RICA,** C\u00d4TE D'IVOIRE,** FRANCE,*** GERMANY,** HAITI,*** INDIA,** IRAN (ISLAMIC REPUBLIC OF),** ISRAEL,** ITALY,** JAPAN,** KENYA,*** LIBERIA,* MEXICO,** MOROCCO,* PAKISTAN,** PARAGUAY,*** PHILIPPINES,* POLAND,** REPUBLIC OF KOREA,* RUSSIAN FEDERATION,*** RWANDA,** SOUTH AFRICA,** TUNISIA,* UNITED KINGDOM OF GREAT BRITAIN AND NORTHERN IRELAND,** UNITED STATES OF AMERICA** and URUGUAY.** \n\n* Term of office expires on 31 December 2025. \n** Term of office expires on 31 December 2026. \n*** Term of office expires on 31 December 2027.",
  "ED_Disclaimer": "The final text of this decision will be contained in document A/79/49 (Vol. II) after editorial review. ",
  "ED_MarkNew": false,
  "ED_MarkUpdated": false,
  "__v": 0,
  "DEC_NotificationSent": true,
  "DEC_NotificationSentTime": "2024-11-15T00:00:00.115Z"
}