{
  "_id": "5fecbd029b661c0917d13b25",
  "ED_Division": "GA",
  "ED_DecisionNumber": "73/531",
  "ED_Type": "Other Decisions",
  "ED_Title": "High-level plenary meeting to mark the twentieth anniversary of the adoption of the Declaration on the Right and Responsibility of Individuals, Groups and Organs of Society to Promote and Protect Universally Recognized Human Rights and Fundamental Freedoms",
  "ED_AgendaItem": "74 (b)",
  "ED_Plenary_Committee": "Plenary",
  "ED_Session": "73rd session of the General Assembly",
  "ED_OriginatingBody": "Plenary",
  "ED_DecisionText": "At its 59th plenary meeting, on 18 December 2018, the General Assembly decided, without setting a precedent, to invite Ms. Michelle Bachelet, the United Nations High Commissioner for Human Rights; Mr. Michel Forst, the United Nations Special Rapporteur on the Situation of Human Rights Defenders; Her Excellency Ine Eriksen S\u00f8reide, Minister of Foreign Affairs of Norway; Ms. Hina Jilani, Advocate Supreme Court of Pakistan, Member of The Elders; Ms. Alice Mogwe, Director of Ditshwanelo - The Botswana Center for Human Rights; and Ms. Florence Simbiri-Jaoko, the Special Envoy of the Global Alliance of National Human Rights Institutions and former Chair of Kenya\u2019s National Human Rights Institution, to make statements at the high-level plenary meeting",
  "ED_Disclaimer": "",
  "ED_MarkNew": false,
  "ED_MarkUpdated": false,
  "DEC_NotificationSent": true,
  "ED_Meeting": [
    {
      "ED_Date": "2018-12-18T05:00:00.000Z",
      "ED_Number": "59th plenary meeting"
    }
  ]
}